CHANGES.txt
MANIFEST.in
README.rst
setup.cfg
setup.py
lettuce_webdriver/__init__.py
lettuce_webdriver/css_selector_steps.py
lettuce_webdriver/django.py
lettuce_webdriver/parallel_bin.py
lettuce_webdriver/parallel_runner.py
lettuce_webdriver/util.py
lettuce_webdriver/webdriver.py
lettuce_webdriver.egg-info/PKG-INFO
lettuce_webdriver.egg-info/SOURCES.txt
lettuce_webdriver.egg-info/dependency_links.txt
lettuce_webdriver.egg-info/entry_points.txt
lettuce_webdriver.egg-info/not-zip-safe
lettuce_webdriver.egg-info/requires.txt
lettuce_webdriver.egg-info/top_level.txt
lettuce_webdriver/tests/__init__.py
lettuce_webdriver/tests/test_css_selector_steps.py
lettuce_webdriver/tests/test_util.py
lettuce_webdriver/tests/test_webdriver.py