Metadata-Version: 1.1
Name: lettuce-webdriver
Version: 0.3.3
Summary: Selenium webdriver extension for lettuce
Home-page: https://github.com/bbangert/lettuce_webdriver/
Author: Nick Pilon, Ben Bangert
Author-email: npilon@gmail.com, ben@groovie.org
License: MIT
Keywords: web lettuce bdd
Platform: UNKNOWN
Classifier: Intended Audience :: Developers
Classifier: Programming Language :: Python
Classifier: Topic :: Internet :: WWW/HTTP
Classifier: Topic :: Software Development :: Testing
